{
  "seed": {
    "secondsUntilRestock": 55,
    "lastRestockAt": 1774220345728,
    "items": [
      {
        "name": "Carrot",
        "stock": 19
      },
      {
        "name": "Cabbage",
        "stock": 3
      },
      {
        "name": "Strawberry",
        "stock": 1
      },
      {
        "name": "Aloe",
        "stock": 10
      },
      {
        "name": "Clover",
        "stock": 3
      },
      {
        "name": "Beet",
        "stock": 6
      },
      {
        "name": "FavaBean",
        "stock": 2
      },
      {
        "name": "Blueberry",
        "stock": 5
      },
      {
        "name": "Tomato",
        "stock": 1
      },
      {
        "name": "Lily",
        "stock": 3
      },
      {
        "name": "Peach",
        "stock": 1
      }
    ]
  },
  "egg": {
    "secondsUntilRestock": 55,
    "lastRestockAt": 1774219643762,
    "items": [
      {
        "name": "CommonEgg",
        "stock": 1
      },
      {
        "name": "RareEgg",
        "stock": 1
      }
    ]
  },
  "decor": {
    "secondsUntilRestock": 55,
    "lastRestockAt": 1774217033677,
    "items": [
      {
        "name": "SmallRock",
        "stock": 3
      },
      {
        "name": "MediumRock",
        "stock": 3
      },
      {
        "name": "HayBale",
        "stock": 1
      },
      {
        "name": "WoodBench",
        "stock": 2
      },
      {
        "name": "WoodArch",
        "stock": 2
      },
      {
        "name": "WoodBirdhouse",
        "stock": 1
      },
      {
        "name": "StoneBench",
        "stock": 2
      },
      {
        "name": "StoneArch",
        "stock": 2
      },
      {
        "name": "FeedingTrough",
        "stock": 1
      },
      {
        "name": "DecorShed",
        "stock": 1
      },
      {
        "name": "PetHutch",
        "stock": 1
      },
      {
        "name": "SeedSilo",
        "stock": 1
      }
    ]
  }
}
