{
  "seed": {
    "secondsUntilRestock": 161,
    "lastRestockAt": 1775244439846,
    "items": [
      {
        "name": "Carrot",
        "stock": 19
      },
      {
        "name": "Cabbage",
        "stock": 3
      },
      {
        "name": "Strawberry",
        "stock": 5
      },
      {
        "name": "Aloe",
        "stock": 5
      },
      {
        "name": "Beet",
        "stock": 6
      },
      {
        "name": "FavaBean",
        "stock": 3
      },
      {
        "name": "OrangeTulip",
        "stock": 11
      },
      {
        "name": "Tomato",
        "stock": 1
      },
      {
        "name": "Banana",
        "stock": 3
      },
      {
        "name": "Lily",
        "stock": 2
      },
      {
        "name": "BurrosTail",
        "stock": 3
      }
    ]
  },
  "egg": {
    "secondsUntilRestock": 161,
    "lastRestockAt": 1775244439846,
    "items": [
      {
        "name": "CommonEgg",
        "stock": 2
      },
      {
        "name": "UncommonEgg",
        "stock": 1
      }
    ]
  },
  "decor": {
    "secondsUntilRestock": 1961,
    "lastRestockAt": 1775243247817,
    "items": [
      {
        "name": "SmallRock",
        "stock": 5
      },
      {
        "name": "MediumRock",
        "stock": 3
      },
      {
        "name": "HayBale",
        "stock": 2
      },
      {
        "name": "StringLights",
        "stock": 2
      },
      {
        "name": "WoodBench",
        "stock": 2
      },
      {
        "name": "WoodArch",
        "stock": 2
      },
      {
        "name": "WoodBridge",
        "stock": 2
      },
      {
        "name": "WoodLampPost",
        "stock": 1
      },
      {
        "name": "WoodWindmill",
        "stock": 1
      },
      {
        "name": "StoneBench",
        "stock": 2
      },
      {
        "name": "StoneArch",
        "stock": 2
      },
      {
        "name": "MarbleBench",
        "stock": 1
      },
      {
        "name": "MarbleArch",
        "stock": 1
      },
      {
        "name": "FeedingTrough",
        "stock": 1
      },
      {
        "name": "DecorShed",
        "stock": 1
      },
      {
        "name": "PetHutch",
        "stock": 1
      },
      {
        "name": "SeedSilo",
        "stock": 1
      }
    ]
  }
}
