{
  "seed": {
    "secondsUntilRestock": 106,
    "lastRestockAt": 1773062295451,
    "items": [
      {
        "name": "Carrot",
        "stock": 12
      },
      {
        "name": "Cabbage",
        "stock": 3
      },
      {
        "name": "Strawberry",
        "stock": 6
      },
      {
        "name": "Aloe",
        "stock": 7
      },
      {
        "name": "Beet",
        "stock": 9
      },
      {
        "name": "Blueberry",
        "stock": 5
      },
      {
        "name": "OrangeTulip",
        "stock": 20
      },
      {
        "name": "Tomato",
        "stock": 1
      },
      {
        "name": "Daffodil",
        "stock": 3
      },
      {
        "name": "Echeveria",
        "stock": 2
      },
      {
        "name": "Coconut",
        "stock": 1
      },
      {
        "name": "Camellia",
        "stock": 1
      },
      {
        "name": "VioletCort",
        "stock": 7
      }
    ]
  },
  "egg": {
    "secondsUntilRestock": 706,
    "lastRestockAt": 1773062295451,
    "items": [
      {
        "name": "CommonEgg",
        "stock": 3
      }
    ]
  },
  "decor": {
    "secondsUntilRestock": 2506,
    "lastRestockAt": 1773062295451,
    "items": [
      {
        "name": "SmallRock",
        "stock": 5
      },
      {
        "name": "MediumRock",
        "stock": 3
      },
      {
        "name": "StringLights",
        "stock": 2
      },
      {
        "name": "WoodBench",
        "stock": 2
      },
      {
        "name": "WoodArch",
        "stock": 2
      },
      {
        "name": "WoodPergola",
        "stock": 2
      },
      {
        "name": "WoodLampPost",
        "stock": 1
      },
      {
        "name": "StoneBench",
        "stock": 2
      },
      {
        "name": "StoneArch",
        "stock": 2
      },
      {
        "name": "MarbleBench",
        "stock": 1
      },
      {
        "name": "FeedingTrough",
        "stock": 1
      },
      {
        "name": "DecorShed",
        "stock": 1
      },
      {
        "name": "PetHutch",
        "stock": 1
      },
      {
        "name": "SeedSilo",
        "stock": 1
      }
    ]
  }
}
